ultimodel/AttractionFactors.py
ultimodel/CreateNetwork.py
ultimodel/DistributeTraffic.py
ultimodel/Matrices.py
ultimodel/__init__.py
ultimodel-1.0.1.dist-info/LICENSE
ultimodel-1.0.1.dist-info/METADATA
ultimodel-1.0.1.dist-info/WHEEL
ultimodel-1.0.1.dist-info/top_level.txt
ultimodel-1.0.1.dist-info/RECORD
