Metadata-Version: 2.1
Name: ultimodel
Version: 1.0.1
Summary: Universal transport distribution model
Home-page: https://github.com/DLR-VF/ULTImodel
Author: German Aerospace Center - DLR (Nina Thomsen)
Author-email: nina.thomsen@dlr.de
License: MIT
Project-URL: Documentation, https://ultimodel.readthedocs.io/
Project-URL: Source, https://github.com/DLR-VF/ULTImodel
Project-URL: Bug Tracker, https://github.com/DLR-VF/ULTImodel/issues 
License-File: LICENSE
Requires-Dist: pandas
Requires-Dist: numpy
Requires-Dist: geopandas
Requires-Dist: shapely
Requires-Dist: osmnx
Requires-Dist: networkx
Requires-Dist: tqdm
Requires-Dist: requests
Requires-Dist: scikit-learn
Requires-Dist: scipy
